LICENSE
README.md
setup.py
cosi_atmosphere/__init__.py
cosi_atmosphere.egg-info/PKG-INFO
cosi_atmosphere.egg-info/SOURCES.txt
cosi_atmosphere.egg-info/dependency_links.txt
cosi_atmosphere.egg-info/requires.txt
cosi_atmosphere.egg-info/top_level.txt
cosi_atmosphere/response/AtmosphericProfile.py
cosi_atmosphere/response/MassModels.py
cosi_atmosphere/response/ProcessSims.py
cosi_atmosphere/response/ProcessSphericalSims.py
cosi_atmosphere/response/ProcessSphericalSimsRep2.py
cosi_atmosphere/response/RunSims.py
cosi_atmosphere/response/TPCalc.py
cosi_atmosphere/response/__init__.py
cosi_atmosphere/response/data_files/Atmosphere.BestCrabDay.geo
cosi_atmosphere/response/data_files/TP_33km.npy
cosi_atmosphere/response/data_files/mass_attenuation_coefficients_N2-78_O2-22.dat