Metadata-Version: 2.1
Name: cosi_atmosphere
Version: 0.1.7
Summary: Tools for calculating atmospheric response and background
Home-page: https://github.com/cositools/cosi-atmosphere.git
Author: COSI Team
Author-email: christopher.m.karwin@nasa.gov
License-File: LICENSE
Requires-Dist: histpy
Requires-Dist: pandas
Requires-Dist: healpy
Requires-Dist: pymsis
